core_evals
lm_eval
